digitalai/release/__init__.py
digitalai/release/v1/README.md
digitalai/release/v1/__init__.py
digitalai/release/v1/api_client.py
digitalai/release/v1/configuration.py
digitalai/release/v1/exceptions.py
digitalai/release/v1/model_utils.py
digitalai/release/v1/rest.py
digitalai/release/v1/api/__init__.py
digitalai/release/v1/api/activity_logs_api.py
digitalai/release/v1/api/application_api.py
digitalai/release/v1/api/configuration_api.py
digitalai/release/v1/api/delivery_api.py
digitalai/release/v1/api/delivery_pattern_api.py
digitalai/release/v1/api/dsl_api.py
digitalai/release/v1/api/environment_api.py
digitalai/release/v1/api/environment_label_api.py
digitalai/release/v1/api/environment_reservation_api.py
digitalai/release/v1/api/environment_stage_api.py
digitalai/release/v1/api/facet_api.py
digitalai/release/v1/api/folder_api.py
digitalai/release/v1/api/permissions_api.py
digitalai/release/v1/api/phase_api.py
digitalai/release/v1/api/planner_api.py
digitalai/release/v1/api/release_api.py
digitalai/release/v1/api/release_group_api.py
digitalai/release/v1/api/report_api.py
digitalai/release/v1/api/risk_api.py
digitalai/release/v1/api/risk_assessment_api.py
digitalai/release/v1/api/roles_api.py
digitalai/release/v1/api/task_api.py
digitalai/release/v1/api/template_api.py
digitalai/release/v1/api/triggers_api.py
digitalai/release/v1/api/user_api.py
digitalai/release/v1/apis/__init__.py
digitalai/release/v1/model/__init__.py
digitalai/release/v1/model/abort_release.py
digitalai/release/v1/model/activity_log_entry.py
digitalai/release/v1/model/application_filters.py
digitalai/release/v1/model/application_form.py
digitalai/release/v1/model/application_view.py
digitalai/release/v1/model/attachment.py
digitalai/release/v1/model/base_application_view.py
digitalai/release/v1/model/base_environment_view.py
digitalai/release/v1/model/blackout_metadata.py
digitalai/release/v1/model/blackout_period.py
digitalai/release/v1/model/bulk_action_result_view.py
digitalai_release_api_stubs-25.1.0.dist-info/METADATA
digitalai_release_api_stubs-25.1.0.dist-info/WHEEL
digitalai_release_api_stubs-25.1.0.dist-info/licenses/LICENSE
digitalai_release_api_stubs-25.1.0.dist-info/RECORD
