Metadata-Version: 2.4
Name: digitalai-release-api-stubs
Version: 25.1.0
Summary: Digital.ai Release API Stubs
Project-URL: Homepage, https://digital.ai/
Project-URL: Documentation, https://docs.digital.ai/release/docs/category/python-sdk
Author-email: "Digital.ai" <pypi-devops@digital.ai>
License-File: LICENSE
Classifier: Development Status :: 5 - Production/Stable
Classifier: Intended Audience :: Developers
Classifier: License :: OSI Approved :: MIT License
Classifier: Operating System :: OS Independent
Classifier: Programming Language :: Python :: 3
Classifier: Programming Language :: Python :: 3.8
Classifier: Programming Language :: Python :: 3.9
Classifier: Programming Language :: Python :: 3.10
Classifier: Programming Language :: Python :: 3.11
Classifier: Programming Language :: Python :: 3.12
Classifier: Topic :: Software Development :: Libraries
Requires-Python: >=3.8
Requires-Dist: urllib3>=1.25.3
